{
    "Sources": [
        {
            "source": "2MASS J2320292+412341",
            "ra": 350.1221,
            "dec": 41.3949,
            "epoch": null,
            "equinox": "2000",
            "shortname": null,
            "reference": "Bard14",
            "other_references": null,
            "comments": null
        }
    ],
    "Names": [
        {
            "other_name": "2MASS J2320292+412341"
        }
    ],
    "Photometry": [
        {
            "band": "WFCAM.H",
            "magnitude": 13.829,
            "magnitude_error": 0.041,
            "telescope": "UKIRT",
            "epoch": null,
            "comments": "WFCAM filter is a guess. Check reference for actual filter and telescope used. ",
            "regime": null,
            "reference": "Best20.42"
        },
        {
            "band": "WFCAM.J",
            "magnitude": 14.495,
            "magnitude_error": 0.004,
            "telescope": "UKIRT",
            "epoch": null,
            "comments": "WFCAM filter is a guess. Check reference for actual filter and telescope used. ",
            "regime": null,
            "reference": "Schn23.ace9"
        },
        {
            "band": "WFCAM.K",
            "magnitude": 13.145,
            "magnitude_error": 0.004,
            "telescope": "UKIRT",
            "epoch": null,
            "comments": "WFCAM filter is a guess. Check reference for actual filter and telescope used. ",
            "regime": null,
            "reference": "Schn23.ace9"
        }
    ],
    "ProperMotions": [
        {
            "mu_ra": 164.0,
            "mu_ra_error": 5.2,
            "mu_dec": 50.8,
            "mu_dec_error": 6.2,
            "adopted": true,
            "comments": null,
            "reference": "Gagn15.73"
        }
    ],
    "SpectralTypes": [
        {
            "spectral_type_string": "M9.8",
            "spectral_type_code": 69.8,
            "spectral_type_error": null,
            "regime": "nir",
            "adopted": null,
            "photometric": null,
            "comments": null,
            "reference": "Bard14"
        }
    ]
}