{
    "Sources": [
        {
            "source": "CWISEP J040351.00-491605.6",
            "ra": 60.9625,
            "dec": -49.26822222222222,
            "epoch": null,
            "equinox": null,
            "shortname": null,
            "reference": "Meis20.74",
            "other_references": null,
            "comments": null
        }
    ],
    "CompanionRelationships": [
        {
            "companion_name": "UCAC4 204-003910",
            "projected_separation_arcsec": 33.0,
            "projected_separation_error": null,
            "relationship": "Child",
            "comments": null,
            "reference": "Roth24",
            "other_companion_names": "UCAC4 204-003910"
        }
    ],
    "Names": [
        {
            "other_name": "CWISE J040351.12-491605.4"
        },
        {
            "other_name": "CWISEP J040351.00-491605.6"
        }
    ],
    "Photometry": [
        {
            "band": "IRAC.I1",
            "magnitude": 18.12,
            "magnitude_error": 0.13,
            "telescope": "Spitzer",
            "epoch": null,
            "comments": null,
            "regime": null,
            "reference": "Meis20.74"
        },
        {
            "band": "IRAC.I2",
            "magnitude": 16.13,
            "magnitude_error": 0.03,
            "telescope": "Spitzer",
            "epoch": null,
            "comments": null,
            "regime": null,
            "reference": "Meis20.74"
        }
    ],
    "SpectralTypes": [
        {
            "spectral_type_string": "(T7)",
            "spectral_type_code": 87.0,
            "spectral_type_error": 2.0,
            "regime": "nir",
            "adopted": true,
            "photometric": true,
            "comments": null,
            "reference": "Roth24"
        },
        {
            "spectral_type_string": "T8.5",
            "spectral_type_code": 88.5,
            "spectral_type_error": null,
            "regime": "nir",
            "adopted": null,
            "photometric": null,
            "comments": null,
            "reference": "Meis20.74"
        }
    ]
}