{
    "Sources": [
        {
            "source": "LHS 2026",
            "ra": 128.127,
            "dec": -1.5774,
            "epoch": null,
            "equinox": "2000",
            "shortname": null,
            "reference": "Bess91.662",
            "other_references": null,
            "comments": null
        }
    ],
    "Names": [
        {
            "other_name": "2MASS J08323047-0134380"
        },
        {
            "other_name": "Gaia DR2 3073118648694573312"
        },
        {
            "other_name": "Gaia EDR3 3073118648694573312"
        },
        {
            "other_name": "LHS 2026"
        },
        {
            "other_name": "ULAS J083230.54-013441.3"
        }
    ],
    "Parallaxes": [
        {
            "parallax": 50.91,
            "parallax_error": 0.5,
            "adopted": false,
            "comments": null,
            "reference": "Dahn17"
        },
        {
            "parallax": 49.09000983664384,
            "parallax_error": 0.12122737302347135,
            "adopted": false,
            "comments": null,
            "reference": "GaiaDR2"
        },
        {
            "parallax": 48.79825403419688,
            "parallax_error": 0.06616959720849991,
            "adopted": true,
            "comments": null,
            "reference": "GaiaEDR3"
        }
    ],
    "Photometry": [
        {
            "band": "2MASS.H",
            "magnitude": 11.477,
            "magnitude_error": 0.021,
            "telescope": "2MASS",
            "epoch": null,
            "comments": null,
            "regime": null,
            "reference": "Cutr03"
        },
        {
            "band": "2MASS.J",
            "magnitude": 12.035,
            "magnitude_error": 0.023,
            "telescope": "2MASS",
            "epoch": null,
            "comments": null,
            "regime": null,
            "reference": "Cutr03"
        },
        {
            "band": "2MASS.Ks",
            "magnitude": 11.142,
            "magnitude_error": 0.023,
            "telescope": "2MASS",
            "epoch": null,
            "comments": null,
            "regime": null,
            "reference": "Cutr03"
        },
        {
            "band": "GAIA2.G",
            "magnitude": 15.878148078918457,
            "magnitude_error": 0.0007542006544424456,
            "telescope": "Gaia",
            "epoch": null,
            "comments": null,
            "regime": null,
            "reference": "GaiaDR2"
        },
        {
            "band": "GAIA2.Grp",
            "magnitude": 14.40396499633789,
            "magnitude_error": 0.002687689410488129,
            "telescope": "Gaia",
            "epoch": null,
            "comments": null,
            "regime": null,
            "reference": "GaiaDR2"
        },
        {
            "band": "GAIA3.G",
            "magnitude": 15.851377487182617,
            "magnitude_error": 0.0007999776366424386,
            "telescope": "Gaia",
            "epoch": null,
            "comments": null,
            "regime": null,
            "reference": "GaiaEDR3"
        },
        {
            "band": "GAIA3.Grp",
            "magnitude": 14.403045654296875,
            "magnitude_error": 0.001352061410779531,
            "telescope": "Gaia",
            "epoch": null,
            "comments": null,
            "regime": null,
            "reference": "GaiaEDR3"
        },
        {
            "band": "WFCAM.H",
            "magnitude": 11.521,
            "magnitude_error": 0.001,
            "telescope": "UKIRT",
            "epoch": null,
            "comments": null,
            "regime": null,
            "reference": "Lawr12"
        },
        {
            "band": "WFCAM.J",
            "magnitude": 11.972,
            "magnitude_error": 0.001,
            "telescope": "UKIRT",
            "epoch": null,
            "comments": null,
            "regime": null,
            "reference": "WFAU19"
        },
        {
            "band": "WFCAM.K",
            "magnitude": 11.136,
            "magnitude_error": 0.001,
            "telescope": "UKIRT",
            "epoch": null,
            "comments": null,
            "regime": null,
            "reference": "Lawr12"
        },
        {
            "band": "WFCAM.Y",
            "magnitude": 12.885,
            "magnitude_error": 0.001,
            "telescope": "UKIRT",
            "epoch": null,
            "comments": null,
            "regime": null,
            "reference": "Lawr12"
        }
    ],
    "ProperMotions": [
        {
            "mu_ra": 164.0,
            "mu_ra_error": 1.63,
            "mu_dec": -468.31,
            "mu_dec_error": 0.64,
            "adopted": false,
            "comments": null,
            "reference": "Dahn17"
        },
        {
            "mu_ra": 159.5819731357205,
            "mu_ra_error": 0.20335435888075404,
            "mu_dec": -471.9803087530119,
            "mu_dec_error": 0.14872056222704788,
            "adopted": false,
            "comments": null,
            "reference": "GaiaDR2"
        },
        {
            "mu_ra": 158.90536720628114,
            "mu_ra_error": 0.07792649418115616,
            "mu_dec": -471.6279539737189,
            "mu_dec_error": 0.059515196830034256,
            "adopted": true,
            "comments": null,
            "reference": "GaiaEDR3"
        }
    ],
    "SpectralTypes": [
        {
            "spectral_type_string": "M6",
            "spectral_type_code": 66.0,
            "spectral_type_error": null,
            "regime": "optical",
            "adopted": null,
            "photometric": null,
            "comments": null,
            "reference": "Henr04"
        }
    ]
}