{
    "Sources": [
        {
            "source": "PSO J052.2746+13.3754",
            "ra": 52.2736,
            "dec": 13.3755,
            "epoch": null,
            "equinox": "2000",
            "shortname": null,
            "reference": "Best20.257",
            "other_references": null,
            "comments": null
        }
    ],
    "Names": [
        {
            "other_name": "2MASS J03290567+1322317"
        },
        {
            "other_name": "PSO J052.2746+13.3754"
        }
    ],
    "Parallaxes": [
        {
            "parallax": 44.3,
            "parallax_error": 3.0,
            "adopted": true,
            "comments": null,
            "reference": "Best20.257"
        }
    ],
    "Photometry": [
        {
            "band": "2MASS.H",
            "magnitude": 15.837,
            "magnitude_error": 0.123,
            "telescope": "2MASS",
            "epoch": null,
            "comments": null,
            "regime": null,
            "reference": "Cutr03"
        },
        {
            "band": "2MASS.J",
            "magnitude": 16.479,
            "magnitude_error": 0.108,
            "telescope": "2MASS",
            "epoch": null,
            "comments": null,
            "regime": null,
            "reference": "Cutr03"
        },
        {
            "band": "2MASS.Ks",
            "magnitude": 15.606,
            "magnitude_error": 0.275,
            "telescope": "2MASS",
            "epoch": null,
            "comments": null,
            "regime": null,
            "reference": "Cutr03"
        },
        {
            "band": "WFCAM.J",
            "magnitude": 16.207,
            "magnitude_error": 0.012,
            "telescope": "UKIRT",
            "epoch": null,
            "comments": "WFCAM filter is a guess. Check reference for actual filter and telescope used. ",
            "regime": null,
            "reference": "Schn23.ace9"
        },
        {
            "band": "WFCAM.K",
            "magnitude": 15.884,
            "magnitude_error": 0.028,
            "telescope": "UKIRT",
            "epoch": null,
            "comments": "WFCAM filter is a guess. Check reference for actual filter and telescope used. ",
            "regime": null,
            "reference": "Schn23.ace9"
        }
    ],
    "ProperMotions": [
        {
            "mu_ra": 273.0,
            "mu_ra_error": 2.0,
            "mu_dec": -20.7,
            "mu_dec_error": 2.0,
            "adopted": null,
            "comments": null,
            "reference": "Best20.257"
        }
    ],
    "SpectralTypes": [
        {
            "spectral_type_string": "T3.5",
            "spectral_type_code": 83.5,
            "spectral_type_error": null,
            "regime": "nir",
            "adopted": null,
            "photometric": null,
            "comments": null,
            "reference": "Best20.257"
        }
    ]
}