{
    "Sources": [
        {
            "source": "PSO J271.8353+46.9326",
            "ra": 271.8357,
            "dec": 46.9331,
            "epoch": null,
            "equinox": null,
            "shortname": null,
            "reference": "Alle16.PhDT",
            "other_references": null,
            "comments": null
        }
    ],
    "Names": [
        {
            "other_name": "LSPM J1807+4655"
        },
        {
            "other_name": "PSO J271.8353+46.9326"
        }
    ],
    "Photometry": [
        {
            "band": "WISE.W1",
            "magnitude": 13.059,
            "magnitude_error": 0.011,
            "telescope": null,
            "epoch": null,
            "comments": null,
            "reference": "Maro21"
        },
        {
            "band": "WISE.W2",
            "magnitude": 12.857,
            "magnitude_error": 0.009,
            "telescope": null,
            "epoch": null,
            "comments": null,
            "reference": "Maro21"
        },
        {
            "band": "WISE.W3",
            "magnitude": 12.019,
            "magnitude_error": 0.217,
            "telescope": null,
            "epoch": null,
            "comments": null,
            "reference": "Cutr13"
        }
    ]
}