{
    "Sources": [
        {
            "source": "SDSS J172545.59+640501.2",
            "ra": 261.4397,
            "dec": 64.0836,
            "epoch": null,
            "equinox": "2000",
            "shortname": null,
            "reference": "Kell15",
            "other_references": null,
            "comments": null
        }
    ],
    "Names": [
        {
            "other_name": "SDSS J172545.59+640501.2"
        }
    ],
    "Photometry": [
        {
            "band": "WISE.W1",
            "magnitude": 15.397,
            "magnitude_error": 0.014,
            "telescope": "WISE",
            "epoch": null,
            "comments": null,
            "reference": "Maro21"
        },
        {
            "band": "WISE.W2",
            "magnitude": 15.179,
            "magnitude_error": 0.016,
            "telescope": "WISE",
            "epoch": null,
            "comments": null,
            "reference": "Maro21"
        }
    ],
    "ProperMotions": [
        {
            "mu_ra": -160.3,
            "mu_ra_error": 6.5,
            "mu_dec": 315.4,
            "mu_dec_error": 7.5,
            "adopted": true,
            "comments": null,
            "reference": "Maro21"
        },
        {
            "mu_ra": 126.8,
            "mu_ra_error": 340.3,
            "mu_dec": 596.7,
            "mu_dec_error": 313.0,
            "adopted": false,
            "comments": null,
            "reference": "Zhan09"
        }
    ],
    "SpectralTypes": [
        {
            "spectral_type_string": "L2 pec (blue)",
            "spectral_type_code": 72.0,
            "spectral_type_error": null,
            "regime": "nir",
            "adopted": null,
            "photometric": null,
            "comments": null,
            "reference": "Kell15"
        }
    ]
}