{
    "Sources": [
        {
            "source": "UGCS J084510.66+214817.1",
            "ra": 131.2946,
            "dec": 21.8049,
            "epoch": null,
            "equinox": "2000",
            "shortname": null,
            "reference": "Boud13",
            "other_references": null,
            "comments": null
        }
    ],
    "Names": [
        {
            "other_name": "UGCS J084510.65+214817.0"
        },
        {
            "other_name": "UGCS J084510.66+214817.1"
        }
    ],
    "Photometry": [
        {
            "band": "WFCAM.H",
            "magnitude": 16.689,
            "magnitude_error": 0.023,
            "telescope": "UKIRT",
            "epoch": null,
            "comments": null,
            "regime": null,
            "reference": "Lawr12"
        },
        {
            "band": "WFCAM.J",
            "magnitude": 17.419,
            "magnitude_error": 0.033,
            "telescope": "UKIRT",
            "epoch": null,
            "comments": null,
            "regime": null,
            "reference": "Lawr12"
        },
        {
            "band": "WFCAM.K",
            "magnitude": 16.041,
            "magnitude_error": 0.015,
            "telescope": "UKIRT",
            "epoch": null,
            "comments": null,
            "regime": null,
            "reference": "WFAU19"
        },
        {
            "band": "WFCAM.Y",
            "magnitude": 18.376,
            "magnitude_error": 0.055,
            "telescope": "UKIRT",
            "epoch": null,
            "comments": null,
            "regime": null,
            "reference": "Lawr12"
        }
    ],
    "Spectra": [
        {
            "access_url": "https://bdnyc.s3.amazonaws.com/XShooter/J08451065%2B2148170.txt",
            "original_spectrum": null,
            "local_spectrum": null,
            "regime": "nir",
            "telescope": "ESO VLT",
            "instrument": "XShooter",
            "mode": "Echelle",
            "observation_date": "2017-01-02T00:00:00",
            "comments": null,
            "reference": "Manj20",
            "other_references": null
        }
    ],
    "SpectralTypes": [
        {
            "spectral_type_string": "L0",
            "spectral_type_code": 70.0,
            "spectral_type_error": null,
            "regime": "optical",
            "adopted": null,
            "photometric": null,
            "comments": null,
            "reference": "Boud13"
        }
    ]
}