{
    "Sources": [
        {
            "source": "ULAS J120214.62+073113.8",
            "ra": 180.5609,
            "dec": 7.5208,
            "epoch": null,
            "equinox": "2000",
            "shortname": null,
            "reference": "Lodi12.105",
            "other_references": null,
            "comments": null
        }
    ],
    "Names": [
        {
            "other_name": "SDSS J120214.61+073113.7"
        },
        {
            "other_name": "ULAS J120214.62+073113.8"
        },
        {
            "other_name": "ULAS J120214.64+073112.3"
        }
    ],
    "Photometry": [
        {
            "band": "GAIA2.G",
            "magnitude": 20.222,
            "magnitude_error": 0.006,
            "telescope": "Gaia",
            "epoch": null,
            "comments": null,
            "regime": "optical",
            "reference": "GaiaDR2"
        },
        {
            "band": "WFCAM.H",
            "magnitude": 17.041,
            "magnitude_error": 0.033,
            "telescope": "UKIRT",
            "epoch": null,
            "comments": null,
            "regime": null,
            "reference": "Lodi07.1423"
        },
        {
            "band": "WFCAM.J",
            "magnitude": 17.413,
            "magnitude_error": 0.026,
            "telescope": "UKIRT",
            "epoch": null,
            "comments": null,
            "regime": null,
            "reference": "WFAU19"
        },
        {
            "band": "WFCAM.K",
            "magnitude": 16.902,
            "magnitude_error": 0.051,
            "telescope": "UKIRT",
            "epoch": null,
            "comments": null,
            "regime": null,
            "reference": "Lodi07.1423"
        },
        {
            "band": "WFCAM.Y",
            "magnitude": 18.059,
            "magnitude_error": 0.029,
            "telescope": "UKIRT",
            "epoch": null,
            "comments": null,
            "regime": null,
            "reference": "Lawr12"
        }
    ],
    "ProperMotions": [
        {
            "mu_ra": 80.0,
            "mu_ra_error": 7.0,
            "mu_dec": -332.0,
            "mu_dec_error": 7.0,
            "adopted": true,
            "comments": null,
            "reference": "Lodi12.105"
        }
    ],
    "RadialVelocities": [
        {
            "radial_velocity_km_s": 39.6,
            "radial_velocity_error_km_s": null,
            "adopted": null,
            "comments": null,
            "reference": "West08"
        }
    ],
    "SpectralTypes": [
        {
            "spectral_type_string": "esdM7",
            "spectral_type_code": 67.0,
            "spectral_type_error": null,
            "regime": "optical",
            "adopted": null,
            "photometric": null,
            "comments": null,
            "reference": "Lodi12.105"
        }
    ]
}