{
    "Sources": [
        {
            "source": "WISEA J235456.63-481440.1",
            "ra": 358.7359583333333,
            "dec": -48.24447222222222,
            "epoch": null,
            "equinox": null,
            "shortname": null,
            "reference": "Meis20.123",
            "other_references": null,
            "comments": null
        }
    ],
    "Names": [
        {
            "other_name": "WISEA J235456.63-481440.1"
        }
    ],
    "Photometry": [
        {
            "band": "IRAC.I1",
            "magnitude": 18.09,
            "magnitude_error": 0.08,
            "telescope": "Spitzer",
            "epoch": null,
            "comments": null,
            "regime": null,
            "reference": "Meis20.123"
        },
        {
            "band": "IRAC.I2",
            "magnitude": 15.85,
            "magnitude_error": 0.02,
            "telescope": "Spitzer",
            "epoch": null,
            "comments": null,
            "regime": null,
            "reference": "Meis20.123"
        },
        {
            "band": "WFCAM.H",
            "magnitude": 19.33,
            "magnitude_error": null,
            "telescope": "UKIRT",
            "epoch": null,
            "comments": "WFCAM filter is a guess. Check reference for actual filter and telescope used. ",
            "regime": null,
            "reference": "Meis20.123"
        },
        {
            "band": "WFCAM.J",
            "magnitude": 20.11,
            "magnitude_error": null,
            "telescope": "UKIRT",
            "epoch": null,
            "comments": "WFCAM filter is a guess. Check reference for actual filter and telescope used. ",
            "regime": null,
            "reference": "Meis20.123"
        }
    ],
    "SpectralTypes": [
        {
            "spectral_type_string": "T9.5",
            "spectral_type_code": 89.5,
            "spectral_type_error": null,
            "regime": "nir",
            "adopted": null,
            "photometric": null,
            "comments": null,
            "reference": "Meis20.123"
        }
    ]
}