{
    "Sources": [
        {
            "source": "2MASS J15460540+3749458",
            "ra": 236.5225,
            "dec": 37.8294,
            "epoch": null,
            "equinox": "2000",
            "shortname": null,
            "reference": "Gizi00",
            "other_references": null,
            "comments": null
        }
    ],
    "Names": [
        {
            "other_name": "2MASS J15460540+3749458"
        },
        {
            "other_name": "Gaia DR2 1376315127473879936"
        },
        {
            "other_name": "Gaia EDR3 1376315127473879936"
        }
    ],
    "Parallaxes": [
        {
            "parallax": 28.310473115646698,
            "parallax_error": 0.1394011798516934,
            "adopted": false,
            "comments": null,
            "reference": "GaiaDR2"
        },
        {
            "parallax": 28.1526510478645,
            "parallax_error": 0.07407994568347931,
            "adopted": true,
            "comments": null,
            "reference": "GaiaEDR3"
        }
    ],
    "Photometry": [
        {
            "band": "2MASS.H",
            "magnitude": 11.791,
            "magnitude_error": 0.029,
            "telescope": "2MASS",
            "instrument": "2MASS",
            "epoch": null,
            "comments": null,
            "reference": "Cutr03"
        },
        {
            "band": "2MASS.J",
            "magnitude": 12.435,
            "magnitude_error": 0.024,
            "telescope": "2MASS",
            "instrument": "2MASS",
            "epoch": null,
            "comments": null,
            "reference": "Cutr03"
        },
        {
            "band": "2MASS.Ks",
            "magnitude": 11.407,
            "magnitude_error": 0.02,
            "telescope": "2MASS",
            "instrument": "2MASS",
            "epoch": null,
            "comments": null,
            "reference": "Cutr03"
        },
        {
            "band": "GAIA2.G",
            "magnitude": 16.53107452392578,
            "magnitude_error": 0.001148413461474888,
            "telescope": "Gaia",
            "instrument": "Gaia",
            "epoch": null,
            "comments": null,
            "reference": "GaiaDR2"
        },
        {
            "band": "GAIA2.Grp",
            "magnitude": 15.004971504211426,
            "magnitude_error": 0.005360683973277237,
            "telescope": "Gaia",
            "instrument": "Gaia",
            "epoch": null,
            "comments": null,
            "reference": "GaiaDR2"
        },
        {
            "band": "GAIA3.G",
            "magnitude": 16.524757385253906,
            "magnitude_error": 0.0016909550335532982,
            "telescope": "Gaia",
            "instrument": "Gaia",
            "epoch": null,
            "comments": null,
            "reference": "GaiaEDR3"
        },
        {
            "band": "GAIA3.Grp",
            "magnitude": 15.012925148010254,
            "magnitude_error": 0.0018351390136993042,
            "telescope": "Gaia",
            "instrument": "Gaia",
            "epoch": null,
            "comments": null,
            "reference": "GaiaEDR3"
        }
    ],
    "ProperMotions": [
        {
            "mu_ra": -38.62606750600757,
            "mu_ra_error": 0.21151907908433468,
            "mu_dec": -131.14012029369647,
            "mu_dec_error": 0.26742106183925446,
            "adopted": false,
            "comments": null,
            "reference": "GaiaDR2"
        },
        {
            "mu_ra": -38.570305038557514,
            "mu_ra_error": 0.06750737130641937,
            "mu_dec": -130.07613550528293,
            "mu_dec_error": 0.08631271123886108,
            "adopted": true,
            "comments": null,
            "reference": "GaiaEDR3"
        },
        {
            "mu_ra": -20.0,
            "mu_ra_error": 19.0,
            "mu_dec": -120.0,
            "mu_dec_error": 19.0,
            "adopted": false,
            "comments": null,
            "reference": "Luyt79.2"
        }
    ],
    "Spectra": [
        {
            "spectrum": "https://s3.amazonaws.com/bdnyc/optical_spectra/U11439.fits",
            "original_spectrum": null,
            "local_spectrum": "$BDNYC_spectra/optical_spectra/U11439.fits",
            "regime": "optical",
            "telescope": "KPNO 4m",
            "instrument": "R-C Spec",
            "mode": "Unknown",
            "observation_date": "2003-07-10T00:00:00",
            "comments": null,
            "reference": "Cruz07",
            "other_references": null
        }
    ],
    "SpectralTypes": [
        {
            "spectral_type_string": "M7.5",
            "spectral_type_code": 67.5,
            "spectral_type_error": null,
            "regime": "optical",
            "adopted": null,
            "comments": null,
            "reference": "Gizi00"
        }
    ]
}