{
    "Sources": [
        {
            "source": "2MASS J16360078-0034525",
            "ra": 249.0032505,
            "dec": -0.58125,
            "epoch": null,
            "equinox": null,
            "shortname": "1636-0034",
            "reference": "Fan_00",
            "other_references": null,
            "comments": null
        }
    ],
    "Names": [
        {
            "other_name": "2MASS J16360078-0034525"
        },
        {
            "other_name": "SDSSp J163600.79-003452.6"
        }
    ],
    "Photometry": [
        {
            "band": "2MASS.H",
            "magnitude": 13.904,
            "magnitude_error": 0.043,
            "telescope": "2MASS",
            "instrument": "2MASS",
            "epoch": null,
            "comments": null,
            "reference": "Cutr03"
        },
        {
            "band": "2MASS.J",
            "magnitude": 14.59,
            "magnitude_error": 0.044,
            "telescope": "2MASS",
            "instrument": "2MASS",
            "epoch": null,
            "comments": null,
            "reference": "Cutr03"
        },
        {
            "band": "2MASS.Ks",
            "magnitude": 13.415,
            "magnitude_error": 0.036,
            "telescope": "2MASS",
            "instrument": "2MASS",
            "epoch": null,
            "comments": null,
            "reference": "Cutr03"
        },
        {
            "band": "WISE.W1",
            "magnitude": 12.94,
            "magnitude_error": 0.024,
            "telescope": "WISE",
            "instrument": null,
            "epoch": null,
            "comments": null,
            "reference": "Cutr12"
        },
        {
            "band": "WISE.W2",
            "magnitude": 12.697,
            "magnitude_error": 0.028,
            "telescope": "WISE",
            "instrument": null,
            "epoch": null,
            "comments": null,
            "reference": "Cutr12"
        },
        {
            "band": "WISE.W3",
            "magnitude": 12.411,
            "magnitude_error": 0.421,
            "telescope": "WISE",
            "instrument": null,
            "epoch": null,
            "comments": null,
            "reference": "Cutr12"
        },
        {
            "band": "WISE.W4",
            "magnitude": 9.076,
            "magnitude_error": null,
            "telescope": "WISE",
            "instrument": null,
            "epoch": null,
            "comments": null,
            "reference": "Cutr12"
        }
    ],
    "ProperMotions": [
        {
            "mu_ra": -360.8,
            "mu_ra_error": 1.73,
            "mu_dec": -209.72,
            "mu_dec_error": 1.82,
            "adopted": true,
            "comments": null,
            "reference": "Smar18"
        }
    ],
    "Spectra": [
        {
            "spectrum": "https://s3.amazonaws.com/bdnyc/nir_spectra/U51421_1636-0034.fits",
            "original_spectrum": null,
            "local_spectrum": "$BDNYC_spectra/nir_spectra/U51421_1636-0034.fits",
            "regime": "nir",
            "telescope": "IRTF",
            "instrument": "SpeX",
            "mode": "Prism",
            "observation_date": "2008-07-30T00:00:00",
            "comments": "None",
            "reference": "Bard14",
            "other_references": null
        }
    ],
    "SpectralTypes": [
        {
            "spectral_type_string": "M9.0",
            "spectral_type_code": 69.0,
            "spectral_type_error": null,
            "regime": "nir_UCD",
            "adopted": null,
            "comments": null,
            "reference": "Bard14"
        },
        {
            "spectral_type_string": "L0",
            "spectral_type_code": 70.0,
            "spectral_type_error": null,
            "regime": "optical",
            "adopted": null,
            "comments": null,
            "reference": "Fan_00"
        }
    ]
}