{
    "Sources": [
        {
            "source": "2MASS J17312974+2721233",
            "ra": 262.873917,
            "dec": 27.356472,
            "epoch": null,
            "equinox": null,
            "shortname": "1731+2721",
            "reference": "Reid08.1290",
            "other_references": null,
            "comments": null
        }
    ],
    "Names": [
        {
            "other_name": "2MASS J17312974+2721233"
        },
        {
            "other_name": "Gaia DR2 4595127343251508992"
        },
        {
            "other_name": "Gaia EDR3 4595127343251508992"
        },
        {
            "other_name": "LSPM J1731+2721"
        }
    ],
    "Parallaxes": [
        {
            "parallax": 83.73638648041123,
            "parallax_error": 0.11819056964481768,
            "adopted": false,
            "comments": null,
            "reference": "GaiaDR2"
        },
        {
            "parallax": 83.6539942300634,
            "parallax_error": 0.08501505851745605,
            "adopted": true,
            "comments": null,
            "reference": "GaiaEDR3"
        }
    ],
    "Photometry": [
        {
            "band": "2MASS.H",
            "magnitude": 11.391,
            "magnitude_error": 0.03,
            "telescope": "2MASS",
            "instrument": "2MASS",
            "epoch": null,
            "comments": null,
            "reference": "Cutr03"
        },
        {
            "band": "2MASS.J",
            "magnitude": 12.094,
            "magnitude_error": 0.027,
            "telescope": "2MASS",
            "instrument": "2MASS",
            "epoch": null,
            "comments": null,
            "reference": "Cutr03"
        },
        {
            "band": "2MASS.Ks",
            "magnitude": 10.914,
            "magnitude_error": 0.021,
            "telescope": "2MASS",
            "instrument": "2MASS",
            "epoch": null,
            "comments": null,
            "reference": "Cutr03"
        },
        {
            "band": "GAIA2.G",
            "magnitude": 16.803638458251953,
            "magnitude_error": 0.0012842890788160042,
            "telescope": "Gaia",
            "instrument": "Gaia",
            "epoch": null,
            "comments": null,
            "reference": "GaiaDR2"
        },
        {
            "band": "GAIA2.Grp",
            "magnitude": 15.205618858337402,
            "magnitude_error": 0.0059068397453591395,
            "telescope": "Gaia",
            "instrument": "Gaia",
            "epoch": null,
            "comments": null,
            "reference": "GaiaDR2"
        },
        {
            "band": "GAIA3.G",
            "magnitude": 16.806903839111328,
            "magnitude_error": 0.0013699937429677731,
            "telescope": "Gaia",
            "instrument": "Gaia",
            "epoch": null,
            "comments": null,
            "reference": "GaiaEDR3"
        },
        {
            "band": "GAIA3.Grp",
            "magnitude": 15.240497589111328,
            "magnitude_error": 0.0022647552879167775,
            "telescope": "Gaia",
            "instrument": "Gaia",
            "epoch": null,
            "comments": null,
            "reference": "GaiaEDR3"
        },
        {
            "band": "WISE.W1",
            "magnitude": 10.597,
            "magnitude_error": 0.023,
            "telescope": "WISE",
            "instrument": null,
            "epoch": null,
            "comments": null,
            "reference": "Cutr12"
        },
        {
            "band": "WISE.W2",
            "magnitude": 10.322,
            "magnitude_error": 0.02,
            "telescope": "WISE",
            "instrument": null,
            "epoch": null,
            "comments": null,
            "reference": "Cutr12"
        },
        {
            "band": "WISE.W3",
            "magnitude": 9.889,
            "magnitude_error": 0.037,
            "telescope": "WISE",
            "instrument": null,
            "epoch": null,
            "comments": null,
            "reference": "Cutr12"
        },
        {
            "band": "WISE.W4",
            "magnitude": 9.075,
            "magnitude_error": null,
            "telescope": "WISE",
            "instrument": null,
            "epoch": null,
            "comments": null,
            "reference": "Cutr12"
        }
    ],
    "ProperMotions": [
        {
            "mu_ra": -90.2118266946926,
            "mu_ra_error": 0.17488280086013808,
            "mu_dec": -252.86944308711242,
            "mu_dec_error": 0.20247884230871036,
            "adopted": false,
            "comments": null,
            "reference": "GaiaDR2"
        },
        {
            "mu_ra": -90.20816934070697,
            "mu_ra_error": 0.077226422727108,
            "mu_dec": -253.25228583352862,
            "mu_dec_error": 0.0910797193646431,
            "adopted": true,
            "comments": null,
            "reference": "GaiaEDR3"
        },
        {
            "mu_ra": -94.64,
            "mu_ra_error": 1.33,
            "mu_dec": -247.84,
            "mu_dec_error": 0.9,
            "adopted": false,
            "comments": null,
            "reference": "Henr18"
        }
    ],
    "Spectra": [
        {
            "spectrum": "https://bdnyc.s3.amazonaws.com/IRS/1731%252B2721_IRS_spectrum.fits",
            "original_spectrum": "https://bdnyc.s3.amazonaws.com/IRS/1731%2B2721_IRS_spectrum.dat",
            "local_spectrum": null,
            "regime": "mir",
            "telescope": "Spitzer",
            "instrument": "IRS",
            "mode": "SL",
            "observation_date": "2005-08-04T00:00:00",
            "comments": "SL2,SL1",
            "reference": "Suar22",
            "other_references": null
        },
        {
            "spectrum": "https://s3.amazonaws.com/bdnyc/SpeX/Prism/U20744.fits",
            "original_spectrum": null,
            "local_spectrum": "$BDNYC_spectra/SpeX/Prism/U20744.fits",
            "regime": "nir",
            "telescope": "IRTF",
            "instrument": "SpeX",
            "mode": "Prism",
            "observation_date": "2005-03-24T00:00:00",
            "comments": null,
            "reference": "Cruz18",
            "other_references": null
        },
        {
            "spectrum": "https://s3.amazonaws.com/bdnyc/optical_spectra/U20744.fits",
            "original_spectrum": null,
            "local_spectrum": "$BDNYC_spectra/optical_spectra/U20744.fits",
            "regime": "optical",
            "telescope": "CTIO 4m",
            "instrument": "R-C Spec",
            "mode": "Unknown",
            "observation_date": "2003-04-22T08:15:43.956000",
            "comments": null,
            "reference": "Reid08.1290",
            "other_references": null
        }
    ],
    "SpectralTypes": [
        {
            "spectral_type_string": "L0: FLD-G",
            "spectral_type_code": 70.0,
            "spectral_type_error": null,
            "regime": "nir_UCD",
            "adopted": null,
            "comments": null,
            "reference": "Alle13"
        },
        {
            "spectral_type_string": "L0",
            "spectral_type_code": 70.0,
            "spectral_type_error": null,
            "regime": "optical",
            "adopted": null,
            "comments": null,
            "reference": "Reid08.1290"
        }
    ]
}