{
    "Sources": [
        {
            "source": "2MASS J22134491-2136079",
            "ra": 333.43712,
            "dec": -21.602194,
            "epoch": null,
            "equinox": null,
            "shortname": "2213-2136",
            "reference": "Cruz07",
            "other_references": null,
            "comments": null
        }
    ],
    "Names": [
        {
            "other_name": "2MASS J22134491-2136079"
        },
        {
            "other_name": "DENIS J221344.8-213608"
        },
        {
            "other_name": "Gaia DR2 6819452113702184192"
        },
        {
            "other_name": "Gaia EDR3 6819452113702184192"
        }
    ],
    "Parallaxes": [
        {
            "parallax": 21.139636196911276,
            "parallax_error": 1.1338218495625092,
            "adopted": false,
            "comments": null,
            "reference": "GaiaDR2"
        },
        {
            "parallax": 20.94595585178747,
            "parallax_error": 0.7627268433570862,
            "adopted": true,
            "comments": null,
            "reference": "GaiaEDR3"
        }
    ],
    "Photometry": [
        {
            "band": "2MASS.H",
            "magnitude": 14.404,
            "magnitude_error": 0.056,
            "telescope": "2MASS",
            "instrument": "2MASS",
            "epoch": null,
            "comments": null,
            "reference": "Cutr03"
        },
        {
            "band": "2MASS.J",
            "magnitude": 15.376,
            "magnitude_error": 0.035,
            "telescope": "2MASS",
            "instrument": "2MASS",
            "epoch": null,
            "comments": null,
            "reference": "Cutr03"
        },
        {
            "band": "2MASS.Ks",
            "magnitude": 13.756,
            "magnitude_error": 0.039,
            "telescope": "2MASS",
            "instrument": "2MASS",
            "epoch": null,
            "comments": null,
            "reference": "Cutr03"
        },
        {
            "band": "GAIA2.G",
            "magnitude": 20.562850952148438,
            "magnitude_error": 0.009811503480515371,
            "telescope": "Gaia",
            "instrument": "Gaia",
            "epoch": null,
            "comments": null,
            "reference": "GaiaDR2"
        },
        {
            "band": "GAIA2.Grp",
            "magnitude": 18.884267807006836,
            "magnitude_error": 0.063327581919088,
            "telescope": "Gaia",
            "instrument": "Gaia",
            "epoch": null,
            "comments": null,
            "reference": "GaiaDR2"
        },
        {
            "band": "GAIA3.G",
            "magnitude": 20.531600952148438,
            "magnitude_error": 0.0073897776686317465,
            "telescope": "Gaia",
            "instrument": "Gaia",
            "epoch": null,
            "comments": null,
            "reference": "GaiaEDR3"
        },
        {
            "band": "GAIA3.Grp",
            "magnitude": 18.94533348083496,
            "magnitude_error": 0.04818927879724418,
            "telescope": "Gaia",
            "instrument": "Gaia",
            "epoch": null,
            "comments": null,
            "reference": "GaiaEDR3"
        },
        {
            "band": "IRAC.I1",
            "magnitude": 12.99,
            "magnitude_error": 0.02,
            "telescope": "Spitzer",
            "instrument": null,
            "epoch": 2007.490410958904,
            "comments": null,
            "reference": "Luhm09.399"
        },
        {
            "band": "IRAC.I2",
            "magnitude": 12.83,
            "magnitude_error": 0.02,
            "telescope": "Spitzer",
            "instrument": null,
            "epoch": 2007.490410958904,
            "comments": null,
            "reference": "Luhm09.399"
        },
        {
            "band": "IRAC.I3",
            "magnitude": 12.58,
            "magnitude_error": 0.03,
            "telescope": "Spitzer",
            "instrument": null,
            "epoch": 2007.490410958904,
            "comments": null,
            "reference": "Luhm09.399"
        },
        {
            "band": "IRAC.I4",
            "magnitude": 12.37,
            "magnitude_error": 0.03,
            "telescope": "Spitzer",
            "instrument": null,
            "epoch": 2007.490410958904,
            "comments": null,
            "reference": "Luhm09.399"
        },
        {
            "band": "WISE.W1",
            "magnitude": 13.229,
            "magnitude_error": 0.027,
            "telescope": "WISE",
            "instrument": null,
            "epoch": null,
            "comments": null,
            "reference": "Cutr12"
        },
        {
            "band": "WISE.W2",
            "magnitude": 12.832,
            "magnitude_error": 0.029,
            "telescope": "WISE",
            "instrument": null,
            "epoch": null,
            "comments": null,
            "reference": "Cutr12"
        },
        {
            "band": "WISE.W3",
            "magnitude": 11.552,
            "magnitude_error": 0.203,
            "telescope": "WISE",
            "instrument": null,
            "epoch": null,
            "comments": null,
            "reference": "Cutr12"
        },
        {
            "band": "WISE.W4",
            "magnitude": 9.07,
            "magnitude_error": null,
            "telescope": "WISE",
            "instrument": null,
            "epoch": null,
            "comments": null,
            "reference": "Cutr12"
        }
    ],
    "ProperMotions": [
        {
            "mu_ra": 53.595018993430045,
            "mu_ra_error": 1.5633857279377095,
            "mu_dec": -72.85986695282027,
            "mu_dec_error": 2.130333792817907,
            "adopted": false,
            "comments": null,
            "reference": "GaiaDR2"
        },
        {
            "mu_ra": 52.31471182913033,
            "mu_ra_error": 0.7508038878440857,
            "mu_dec": -73.83870029020123,
            "mu_dec_error": 0.9066666960716248,
            "adopted": true,
            "comments": null,
            "reference": "GaiaEDR3"
        },
        {
            "mu_ra": 51.5,
            "mu_ra_error": 1.3,
            "mu_dec": -70.6,
            "mu_dec_error": 1.0,
            "adopted": false,
            "comments": null,
            "reference": "Liu_16"
        }
    ],
    "Spectra": [
        {
            "spectrum": "https://s3.amazonaws.com/bdnyc/nir_spectra/U12120_051017.fits",
            "original_spectrum": null,
            "local_spectrum": "$BDNYC_spectra/nir_spectra/U12120_051017.fits",
            "regime": "nir",
            "telescope": "IRTF",
            "instrument": "SpeX",
            "mode": "Prism",
            "observation_date": "2005-10-17T00:00:00",
            "comments": "obs by adam for me. Dagny's better.",
            "reference": "Cruz18",
            "other_references": null
        },
        {
            "spectrum": "https://s3.amazonaws.com/bdnyc/SpeX/Prism/j2213-2136prismtc1.fits",
            "original_spectrum": null,
            "local_spectrum": "$BDNYC_spectra/SpeX/Prism/j2213-2136prismtc1.fits",
            "regime": "nir",
            "telescope": "IRTF",
            "instrument": "SpeX",
            "mode": "Prism",
            "observation_date": "2008-08-29T00:00:00",
            "comments": "obs by Dagny",
            "reference": "Bard14",
            "other_references": null
        },
        {
            "spectrum": "https://bdnyc.s3.amazonaws.com/ISAAC/2M2213_ISAACspec_JHK_nocosmic.fits",
            "original_spectrum": null,
            "local_spectrum": null,
            "regime": "nir",
            "telescope": "ESO VLT U3",
            "instrument": "ISAAC",
            "mode": "SW LRes",
            "observation_date": "2013-08-06T00:00:00",
            "comments": null,
            "reference": "Manj14",
            "other_references": null
        },
        {
            "spectrum": "https://s3.amazonaws.com/bdnyc/optical_spectra/U12120.fits",
            "original_spectrum": null,
            "local_spectrum": "$BDNYC_spectra/optical_spectra/U12120.fits",
            "regime": "optical",
            "telescope": "Gemini South",
            "instrument": "GMOS-S",
            "mode": "Unknown",
            "observation_date": "2005-09-08T00:00:00",
            "comments": null,
            "reference": "Cruz09",
            "other_references": null
        }
    ],
    "SpectralTypes": [
        {
            "spectral_type_string": "L0: VL-G",
            "spectral_type_code": 70.0,
            "spectral_type_error": null,
            "regime": "nir_UCD",
            "adopted": null,
            "comments": null,
            "reference": "Alle13"
        },
        {
            "spectral_type_string": "L0 gamma",
            "spectral_type_code": 70.0,
            "spectral_type_error": null,
            "regime": "optical",
            "adopted": null,
            "comments": null,
            "reference": "Cruz09"
        }
    ]
}