{
    "Sources": [
        {
            "source": "EQ J0623-0456",
            "ra": 95.7914175,
            "dec": -4.940167,
            "epoch": null,
            "equinox": null,
            "shortname": "0623-0456",
            "reference": "Kirk11",
            "comments": null
        }
    ],
    "Names": [
        {
            "other_name": "EQ J0623-0456"
        },
        {
            "other_name": "WISE J062259.13-045610.5"
        },
        {
            "other_name": "WISEPA J062309.94-045624.6"
        }
    ],
    "ProperMotions": [
        {
            "mu_ra": -906.3,
            "mu_ra_error": 1.8,
            "mu_dec": 168.8,
            "mu_dec_error": 1.6,
            "adopted": null,
            "comments": null,
            "reference": "Best20a"
        },
        {
            "mu_ra": -905.2,
            "mu_ra_error": 1.1,
            "mu_dec": 159.9,
            "mu_dec_error": 0.8,
            "adopted": true,
            "comments": null,
            "reference": "Kirk19"
        }
    ]
}