{
    "Sources": [
        {
            "source": "SDSS J104842.70+300650.5",
            "ra": 162.1774,
            "dec": 30.114,
            "epoch": null,
            "equinox": "2000",
            "shortname": null,
            "reference": "Schm10b",
            "comments": null
        }
    ],
    "Names": [
        {
            "other_name": "SDSS J104842.70+300650.5"
        }
    ],
    "ProperMotions": [
        {
            "mu_ra": -140.9,
            "mu_ra_error": 8.2,
            "mu_dec": -6.9,
            "mu_dec_error": 13.4,
            "adopted": true,
            "comments": null,
            "reference": "Gagn15a"
        }
    ]
}