{
    "Sources": [
        {
            "source": "ULAS J020529.62+142114.0",
            "ra": 31.3739,
            "dec": 14.3538,
            "epoch": null,
            "equinox": "2000",
            "shortname": null,
            "reference": "DayJ13",
            "other_references": null,
            "comments": null
        }
    ],
    "Names": [
        {
            "other_name": "ULAS J020529.62+142114.0"
        }
    ],
    "Photometry": [
        {
            "band": "WFCAM.Y",
            "magnitude": 19.141,
            "magnitude_error": 0.065,
            "telescope": "UKIRT",
            "epoch": null,
            "comments": null,
            "reference": "Lawr12"
        }
    ],
    "SpectralTypes": [
        {
            "spectral_type_string": "T1",
            "spectral_type_code": 81.0,
            "spectral_type_error": null,
            "regime": "nir_UCD",
            "adopted": null,
            "comments": null,
            "reference": "DayJ13"
        }
    ]
}