{
    "Sources": [
        {
            "source": "WISEPA J022623.98-021142.8",
            "ra": 36.6,
            "dec": -2.1952,
            "epoch": null,
            "equinox": "2000",
            "shortname": null,
            "reference": "Kirk11",
            "comments": null
        }
    ],
    "Names": [
        {
            "other_name": "WISEPA J022623.98-021142.8"
        }
    ],
    "Parallaxes": [
        {
            "parallax": 51.1,
            "parallax_error": 2.3,
            "adopted": true,
            "comments": null,
            "reference": "Best20a"
        }
    ],
    "ProperMotions": [
        {
            "mu_ra": -291.8,
            "mu_ra_error": 1.8,
            "mu_dec": -433.5,
            "mu_dec_error": 1.4,
            "adopted": true,
            "comments": null,
            "reference": "Best20a"
        },
        {
            "mu_ra": -294.9,
            "mu_ra_error": 2.1,
            "mu_dec": -436.9,
            "mu_dec_error": 1.7,
            "adopted": null,
            "comments": null,
            "reference": "Kirk19"
        }
    ]
}