{
    "Sources": [
        {
            "source": "WISEP J183058.57+454257.9",
            "ra": 277.744035,
            "dec": 45.716083,
            "shortname": "1830+4542",
            "reference": "Kirk11",
            "comments": null
        }
    ],
    "Names": [
        {
            "other_name": "EQ J1830+4542"
        },
        {
            "other_name": "WISE J183058.56+454257.4"
        },
        {
            "other_name": "WISEP J183058.57+454257.9"
        },
        {
            "other_name": "WISEPA J183058.57+454257.9"
        }
    ]
}