{
    "Sources": [
        {
            "source": "WISE J014656.66+423410.0",
            "ra": 26.7360825,
            "dec": 42.569444,
            "epoch": null,
            "equinox": null,
            "shortname": "0146+4234",
            "reference": "Mace13.6",
            "other_references": null,
            "comments": null
        }
    ],
    "Names": [
        {
            "other_name": "WISE J014656.66+423410.0"
        },
        {
            "other_name": "WISE J014656.66+423410.0A"
        },
        {
            "other_name": "WISEA J014656.66+423409.9"
        }
    ],
    "Photometry": [
        {
            "band": "IRAC.I1",
            "magnitude": 17.86,
            "magnitude_error": 0.17,
            "telescope": "Spitzer",
            "instrument": "IRAC",
            "epoch": null,
            "comments": null,
            "reference": "Legg21"
        },
        {
            "band": "IRAC.I2",
            "magnitude": 15.54,
            "magnitude_error": 0.1,
            "telescope": "Spitzer",
            "instrument": "IRAC",
            "epoch": null,
            "comments": null,
            "reference": "Legg21"
        }
    ],
    "ProperMotions": [
        {
            "mu_ra": -452.0,
            "mu_ra_error": 1.2,
            "mu_dec": -27.9,
            "mu_dec_error": 1.2,
            "adopted": true,
            "comments": null,
            "reference": "Kirk19"
        }
    ],
    "SpectralTypes": [
        {
            "spectral_type_string": "T9",
            "spectral_type_code": 89.0,
            "spectral_type_error": null,
            "regime": "nir",
            "adopted": null,
            "comments": null,
            "reference": "Dupu15.102"
        },
        {
            "spectral_type_string": "T9.5",
            "spectral_type_code": 89.5,
            "spectral_type_error": null,
            "regime": "nir_UCD",
            "adopted": null,
            "comments": null,
            "reference": "Legg17"
        }
    ]
}