{
    "Sources": [
        {
            "source": "WISE J173551.72-820900.1",
            "ra": 263.9649,
            "dec": -82.1501,
            "epoch": null,
            "equinox": "2000",
            "shortname": null,
            "reference": "Tinn18",
            "other_references": null,
            "comments": null
        }
    ],
    "Names": [
        {
            "other_name": "WISE J173551.72-820900.1"
        }
    ],
    "ProperMotions": [
        {
            "mu_ra": -250.2,
            "mu_ra_error": 1.9,
            "mu_dec": -257.8,
            "mu_dec_error": 1.8,
            "adopted": true,
            "comments": null,
            "reference": "Kirk19"
        }
    ],
    "SpectralTypes": [
        {
            "spectral_type_string": "T6",
            "spectral_type_code": 86.0,
            "spectral_type_error": null,
            "regime": "nir",
            "adopted": null,
            "comments": null,
            "reference": "Tinn18"
        }
    ]
}